gosyu/__init__.py
gosyu/doc/conf.py
gosyu/doc/index.rst
gosyu/doc/make.bat
gosyu/doc/Makefile
gosyu/doc/module_gosyu.rst
gosyu/doc/README.rst
gosyu/doc/README_ja.rst
gosyu-2.0.6.dist-info/DESCRIPTION.rst
gosyu-2.0.6.dist-info/METADATA
gosyu-2.0.6.dist-info/metadata.json
gosyu-2.0.6.dist-info/RECORD
gosyu-2.0.6.dist-info/top_level.txt
gosyu-2.0.6.dist-info/WHEEL
sphinxcontrib/gosyu.py
sphinxcontrib/__init__.py
sphinxcontrib/gosyu/gosyu.py
sphinxcontrib/gosyu/__init__.py
sphinxcontrib/gosyu/doc/conf.py
sphinxcontrib/gosyu/doc/index.rst
sphinxcontrib/gosyu/doc/make.bat
sphinxcontrib/gosyu/doc/Makefile
sphinxcontrib/gosyu/doc/module_gosyu.rst
sphinxcontrib/gosyu/doc/README.rst
sphinxcontrib/gosyu/doc/README_ja.rst
sphinxcontrib/gosyu/doc/_build/html/index.html
sphinxcontrib/gosyu/doc/_build/html/module_gosyu.html
sphinxcontrib/gosyu/doc/_build/html/README.html
sphinxcontrib/gosyu/doc/_build/html/README_ja.html
sphinxcontrib/gosyu/doc/_build/html/search.html
sphinxcontrib/gosyu/doc/_build/html/searchindex.js
sphinxcontrib/gosyu/doc/_build/html/_sources/index.txt
sphinxcontrib/gosyu/doc/_build/html/_sources/module_gosyu.txt
sphinxcontrib/gosyu/doc/_build/html/_sources/README.txt
sphinxcontrib/gosyu/doc/_build/html/_sources/README_ja.txt
sphinxcontrib/gosyu/doc/_build/html/_static/ajax-loader.gif
sphinxcontrib/gosyu/doc/_build/html/_static/alert_info_32.png
sphinxcontrib/gosyu/doc/_build/html/_static/alert_warning_32.png
sphinxcontrib/gosyu/doc/_build/html/_static/basic.css
sphinxcontrib/gosyu/doc/_build/html/_static/bg-page.png
sphinxcontrib/gosyu/doc/_build/html/_static/bullet_orange.png
sphinxcontrib/gosyu/doc/_build/html/_static/comment-bright.png
sphinxcontrib/gosyu/doc/_build/html/_static/comment-close.png
sphinxcontrib/gosyu/doc/_build/html/_static/comment.png
sphinxcontrib/gosyu/doc/_build/html/_static/doctools.js
sphinxcontrib/gosyu/doc/_build/html/_static/down-pressed.png
sphinxcontrib/gosyu/doc/_build/html/_static/down.png
sphinxcontrib/gosyu/doc/_build/html/_static/file.png
sphinxcontrib/gosyu/doc/_build/html/_static/haiku.css
sphinxcontrib/gosyu/doc/_build/html/_static/jquery-1.11.1.js
